proligent/__init__.py
proligent/model.py
proligent/xml_validate.py
proligent/datawarehouse/__init__.py
proligent/datawarehouse/datawarehouse.py
proligent/datawarehouse/datawarehouse_application_config_xsd.py
proligent/datawarehouse/datawarehouse_assembly_xsd.py
proligent/datawarehouse/datawarehouse_component_unit.py
proligent/datawarehouse/datawarehouse_event_xsd.py
proligent/datawarehouse/datawarehouse_failure.py
proligent/datawarehouse/datawarehouse_measure.py
proligent/datawarehouse/datawarehouse_model.py
proligent/datawarehouse/datawarehouse_operation_cycle.py
proligent/datawarehouse/datawarehouse_operation_run.py
proligent/datawarehouse/datawarehouse_process_run.py
proligent/datawarehouse/datawarehouse_product_unit.py
proligent/datawarehouse/datawarehouse_product_unit_return.py
proligent/datawarehouse/datawarehouse_sequence_run.py
proligent/datawarehouse/datawarehouse_shipment.py
proligent/datawarehouse/datawarehouse_step_run.py
proligent/datawarehouse/datawarehouse_tracked_component_unit_xsd.py
proligent/xsd/Datawarehouse.ApplicationConfig.xsd
proligent/xsd/Datawarehouse.Assembly.xsd
proligent/xsd/Datawarehouse.ComponentUnit.xsd
proligent/xsd/Datawarehouse.Event.xsd
proligent/xsd/Datawarehouse.Failure.xsd
proligent/xsd/Datawarehouse.Measure.xsd
proligent/xsd/Datawarehouse.Model.xsd
proligent/xsd/Datawarehouse.OperationCycle.xsd
proligent/xsd/Datawarehouse.OperationRun.xsd
proligent/xsd/Datawarehouse.ProcessRun.xsd
proligent/xsd/Datawarehouse.ProductUnit.xsd
proligent/xsd/Datawarehouse.ProductUnitReturn.xsd
proligent/xsd/Datawarehouse.SequenceRun.xsd
proligent/xsd/Datawarehouse.Shipment.xsd
proligent/xsd/Datawarehouse.StepRun.xsd
proligent/xsd/Datawarehouse.TrackedComponentUnit.xsd
proligent/xsd/Datawarehouse.xsd
proligent_xml_generator-1.0.0.dist-info/licenses/LICENSE
proligent_xml_generator-1.0.0.dist-info/METADATA
proligent_xml_generator-1.0.0.dist-info/WHEEL
proligent_xml_generator-1.0.0.dist-info/top_level.txt
proligent_xml_generator-1.0.0.dist-info/RECORD
