Metadata-Version: 2.4
Name: proligent-xml-generator
Version: 1.0.0
Summary: Python library for generating Proligent™ XML files.
Author: Ben Engelen, Kaitlin Van de Kerckhove, Philippe Gélinas, Mathieu Bélanger
Maintainer: Philippe Gélinas, Mathieu Bélanger
License-Expression: BSD-3-Clause
Project-URL: Homepage, https://github.com/Averna/proligent-xml-generator-python
Project-URL: Documentation, https://github.com/Averna/proligent-xml-generator-python/blob/main/README.md
Project-URL: Repository, https://github.com/Averna/proligent-xml-generator-python
Project-URL: Tracker, https://github.com/Averna/proligent-xml-generator-python/issues
Project-URL: Changelog, https://github.com/Averna/proligent-xml-generator-python/blob/main/README.md
Keywords: averna,proligent,xml,generator
Classifier: Intended Audience :: Developers
Classifier: Programming Language :: Python :: 3 :: Only
Classifier: Programming Language :: Python :: 3.10
Classifier: Programming Language :: Python :: 3.11
Classifier: Programming Language :: Python :: 3.12
Classifier: Programming Language :: Python :: 3.13
Classifier: Topic :: Software Development :: Libraries
Classifier: Topic :: Utilities
Requires-Python: <3.14,>=3.10
License-File: LICENSE
Requires-Dist: pytz>=2024.1
Requires-Dist: xmlschema>=3.4.3
Requires-Dist: xsdata>=24.5
Dynamic: license-file
